openalea/__init__.py
openalea/container/graph.py
openalea/container/grid.py
openalea/container/id_dict.py
openalea/container/id_generator.py
openalea/container/property_graph.py
openalea/container/version.py
openalea/container/__init__.py
openalea.container-0.1.0.dist-info/DESCRIPTION.rst
openalea.container-0.1.0.dist-info/METADATA
openalea.container-0.1.0.dist-info/metadata.json
openalea.container-0.1.0.dist-info/RECORD
openalea.container-0.1.0.dist-info/top_level.txt
openalea.container-0.1.0.dist-info/WHEEL
