Metadata-Version: 2.0
Name: openalea.container
Version: 0.1.0
Summary: Set of data structures used in openalea such as : graph, grid, topomesh
Home-page: UNKNOWN
Author: revesansparole
Author-email: revesansparole@gmail.com
License: mit
Platform: UNKNOWN
Classifier: Intended Audience :: Developers
Classifier: Programming Language :: Python
Classifier: Programming Language :: Python :: 2
Classifier: Programming Language :: Python :: 2 :: Only
Classifier: Programming Language :: Python :: 2.7
